[{"s":"conatus","r":"HIGH","f":2,"z":7159,"S":0,"c":0,"h":5,"m":0},{"s":"rune-prompt-amplification","r":"HIGH","f":5,"z":7339,"S":1,"c":0,"h":2,"m":0},{"s":"upbit-trading-skill","r":"HIGH","f":5,"z":13168,"S":1,"c":0,"h":18,"m":2},{"s":"dropbox-lite","r":"HIGH","f":5,"z":17028,"S":1,"c":0,"h":18,"m":8},{"s":"pbe-extractor","r":"LOW","f":2,"z":8783,"S":0,"c":0,"h":0,"m":0},{"s":"slipbot","r":"LOW","f":2,"z":5505,"S":0,"c":0,"h":0,"m":0},{"s":"deepbook-cli","r":"MEDIUM","f":2,"z":9041,"S":0,"c":0,"h":0,"m":1},{"s":"dropbox-integration","r":"HIGH","f":10,"z":36325,"S":1,"c":0,"h":49,"m":12},{"s":"slipbot-logseq-importer","r":"LOW","f":2,"z":5041,"S":0,"c":0,"h":0,"m":0},{"s":"slipbot-kindle-importer","r":"LOW","f":2,"z":2903,"S":0,"c":0,"h":0,"m":0},{"s":"snapbyte-digest-api","r":"HIGH","f":4,"z":10622,"S":1,"c":0,"h":3,"m":7},{"s":"dropbox-business","r":"HIGH","f":3,"z":28765,"S":0,"c":0,"h":18,"m":0},{"s":"deepblue-defi-api","r":"HIGH","f":2,"z":5863,"S":0,"c":0,"h":14,"m":0},{"s":"upbit","r":"HIGH","f":2,"z":3396,"S":0,"c":0,"h":2,"m":0},{"s":"raspberry-pi-manager","r":"EXTREME","f":4,"z":21964,"S":1,"c":1,"h":17,"m":9},{"s":"bapbook","r":"HIGH","f":2,"z":14023,"S":0,"c":0,"h":34,"m":0},{"s":"raspberry-pi-camera-service","r":"EXTREME","f":16,"z":99211,"S":1,"c":1,"h":44,"m":47},{"s":"webappbuilder","r":"HIGH","f":4,"z":11822,"S":1,"c":0,"h":9,"m":4},{"s":"integrate-dropbox","r":"HIGH","f":2,"z":6010,"S":0,"c":0,"h":2,"m":1},{"s":"clipboard-manager-tool","r":"HIGH","f":4,"z":7550,"S":1,"c":0,"h":1,"m":0},{"s":"dropbox-sign","r":"HIGH","f":2,"z":6382,"S":0,"c":0,"h":2,"m":1},{"s":"gopass","r":"MEDIUM","f":2,"z":3018,"S":0,"c":0,"h":0,"m":1},{"s":"clipboard-manager","r":"HIGH","f":3,"z":6893,"S":1,"c":0,"h":1,"m":1},{"s":"stdio-skill","r":"HIGH","f":3,"z":11310,"S":1,"c":0,"h":7,"m":1},{"s":"clipboard-knowledge-capture","r":"EXTREME","f":10,"z":21113,"S":1,"c":1,"h":1,"m":3},{"s":"sipbrainstorming","r":"LOW","f":2,"z":4825,"S":0,"c":0,"h":0,"m":0},{"s":"stock-valuation-monitor","r":"HIGH","f":5,"z":78493,"S":1,"c":0,"h":4,"m":0},{"s":"upbit-openapi-skill","r":"HIGH","f":6,"z":8083,"S":1,"c":0,"h":29,"m":0},{"s":"stock-pe-pb-analyzer-skill","r":"HIGH","f":4,"z":31033,"S":1,"c":0,"h":3,"m":1},{"s":"a-share-glossary-tutor","r":"LOW","f":2,"z":1594,"S":0,"c":0,"h":0,"m":0},{"s":"client-flow","r":"MEDIUM","f":2,"z":9695,"S":0,"c":0,"h":0,"m":1},{"s":"mapbox","r":"HIGH","f":4,"z":7415,"S":0,"c":0,"h":1,"m":0},{"s":"clawsy","r":"EXTREME","f":3,"z":24007,"S":0,"c":2,"h":1,"m":0},{"s":"windows-automation","r":"MEDIUM","f":4,"z":10307,"S":1,"c":0,"h":0,"m":3},{"s":"mapbox-integration","r":"HIGH","f":2,"z":4468,"S":0,"c":0,"h":2,"m":1},{"s":"cpbl","r":"HIGH","f":18,"z":78806,"S":1,"c":0,"h":16,"m":4},{"s":"regulation-monitor","r":"HIGH","f":3,"z":23814,"S":1,"c":0,"h":14,"m":2},{"s":"cpbox-news-search","r":"HIGH","f":2,"z":7898,"S":0,"c":0,"h":10,"m":0},{"s":"clipbox","r":"HIGH","f":3,"z":14465,"S":1,"c":0,"h":2,"m":2},{"s":"ipbase","r":"HIGH","f":2,"z":4682,"S":0,"c":0,"h":2,"m":1},{"s":"cpbox-web-search","r":"HIGH","f":2,"z":15542,"S":0,"c":0,"h":13,"m":0},{"s":"cpbox-videos-search","r":"HIGH","f":2,"z":7843,"S":0,"c":0,"h":10,"m":0},{"s":"appbaseio","r":"HIGH","f":2,"z":4988,"S":0,"c":0,"h":2,"m":1},{"s":"afrexai-pharmacy-compliance","r":"HIGH","f":3,"z":5441,"S":0,"c":0,"h":7,"m":0},{"s":"bap-578-baptism","r":"HIGH","f":2,"z":56550,"S":0,"c":0,"h":26,"m":3},{"s":"daily-security-check","r":"HIGH","f":11,"z":30698,"S":0,"c":0,"h":8,"m":9},{"s":"pi-speaker","r":"HIGH","f":3,"z":3818,"S":1,"c":0,"h":1,"m":1},{"s":"kimp-price","r":"HIGH","f":3,"z":4619,"S":1,"c":0,"h":5,"m":0},{"s":"daily-health-report","r":"LOW","f":4,"z":1758,"S":1,"c":0,"h":0,"m":0},{"s":"meganode-skill","r":"HIGH","f":22,"z":410850,"S":0,"c":0,"h":236,"m":0},{"s":"k8s-debug","r":"HIGH","f":9,"z":74059,"S":1,"c":0,"h":9,"m":18},{"s":"macos-wechat-send","r":"HIGH","f":4,"z":19723,"S":1,"c":0,"h":1,"m":1},{"s":"pcec-evomap-integrator","r":"HIGH","f":2,"z":7820,"S":0,"c":0,"h":4,"m":0},{"s":"pc-control","r":"HIGH","f":8,"z":13654,"S":1,"c":0,"h":4,"m":3},{"s":"pco","r":"HIGH","f":2,"z":3537,"S":0,"c":0,"h":1,"m":0},{"s":"pc-operation-security","r":"HIGH","f":3,"z":8436,"S":1,"c":0,"h":3,"m":0},{"s":"pc-monitor-cn","r":"MEDIUM","f":5,"z":5609,"S":1,"c":0,"h":0,"m":2},{"s":"pcclaw","r":"HIGH","f":23,"z":219181,"S":0,"c":0,"h":62,"m":26},{"s":"deepclaw","r":"HIGH","f":3,"z":8218,"S":0,"c":0,"h":22,"m":0},{"s":"browser-pc","r":"HIGH","f":5,"z":24641,"S":0,"c":0,"h":12,"m":3},{"s":"mpc-accept-crypto-payments","r":"HIGH","f":6,"z":23808,"S":1,"c":0,"h":23,"m":14},{"s":"cpc-mpqc-competence-tracker-compliance-uk","r":"LOW","f":6,"z":4113,"S":0,"c":0,"h":0,"m":0},{"s":"niri-ipc","r":"HIGH","f":6,"z":20237,"S":1,"c":0,"h":1,"m":1},{"s":"github-mpc","r":"HIGH","f":3,"z":7992,"S":0,"c":0,"h":3,"m":0},{"s":"tg-groupchat-setup","r":"HIGH","f":4,"z":6694,"S":1,"c":0,"h":3,"m":1},{"s":"trpc-best-practices","r":"HIGH","f":2,"z":18474,"S":0,"c":0,"h":6,"m":2},{"s":"incident-pcn-evidence-appeal-corrective-actions-uk","r":"LOW","f":7,"z":4615,"S":0,"c":0,"h":0,"m":0},{"s":"aria2-json-rpc","r":"HIGH","f":18,"z":160547,"S":1,"c":0,"h":41,"m":18},{"s":"whistle-rpc","r":"HIGH","f":4,"z":7289,"S":0,"c":0,"h":26,"m":0},{"s":"ipcam","r":"HIGH","f":7,"z":42246,"S":1,"c":0,"h":29,"m":33},{"s":"snapchat","r":"HIGH","f":3,"z":17883,"S":0,"c":0,"h":25,"m":0},{"s":"reminder","r":"MEDIUM","f":3,"z":3046,"S":0,"c":0,"h":0,"m":1},{"s":"billy-sapconet-ssh-bridge","r":"HIGH","f":4,"z":2114,"S":1,"c":0,"h":6,"m":0},{"s":"erpclaw","r":"HIGH","f":68,"z":2329990,"S":1,"c":0,"h":36,"m":65},{"s":"aria2-rpc","r":"HIGH","f":8,"z":41992,"S":1,"c":0,"h":24,"m":0},{"s":"shop","r":"HIGH","f":5,"z":39018,"S":0,"c":0,"h":56,"m":0},{"s":"zipcracker","r":"MEDIUM","f":5,"z":87557,"S":1,"c":0,"h":0,"m":4},{"s":"openclaw-ispconfig","r":"HIGH","f":17,"z":232370,"S":1,"c":0,"h":195,"m":3},{"s":"napcat-qq-bridge-installer","r":"HIGH","f":7,"z":50731,"S":1,"c":0,"h":34,"m":13},{"s":"meeting-prep","r":"HIGH","f":2,"z":3835,"S":0,"c":0,"h":4,"m":6},{"s":"openclaw-pc-security","r":"HIGH","f":16,"z":99699,"S":1,"c":0,"h":7,"m":20},{"s":"opc-essentials","r":"LOW","f":4,"z":15962,"S":0,"c":0,"h":0,"m":0},{"s":"crypto-whale-monitor","r":"HIGH","f":5,"z":6044,"S":1,"c":0,"h":8,"m":2},{"s":"mole-mac-cleanup","r":"HIGH","f":2,"z":4047,"S":0,"c":0,"h":1,"m":0},{"s":"typescript-pro","r":"HIGH","f":7,"z":46922,"S":0,"c":0,"h":21,"m":0},{"s":"upcoming-concerts","r":"HIGH","f":4,"z":6618,"S":1,"c":0,"h":4,"m":0},{"s":"capcut","r":"HIGH","f":2,"z":1945,"S":0,"c":0,"h":2,"m":0},{"s":"chipchain","r":"HIGH","f":37,"z":271185,"S":1,"c":0,"h":55,"m":9},{"s":"macos-spm-app-packaging","r":"HIGH","f":16,"z":22447,"S":1,"c":0,"h":77,"m":7},{"s":"frappecli","r":"HIGH","f":2,"z":3527,"S":0,"c":0,"h":2,"m":2},{"s":"clawstin","r":"HIGH","f":2,"z":3216,"S":0,"c":0,"h":14,"m":0},{"s":"backupclaw","r":"HIGH","f":4,"z":10981,"S":1,"c":0,"h":31,"m":4},{"s":"clawringhouse","r":"HIGH","f":3,"z":14130,"S":0,"c":0,"h":26,"m":0},{"s":"todoist-td","r":"MEDIUM","f":2,"z":2955,"S":0,"c":0,"h":0,"m":1},{"s":"pumpclaw-agent","r":"HIGH","f":12,"z":117443,"S":1,"c":0,"h":145,"m":1},{"s":"odoo-erp-connector","r":"HIGH","f":30,"z":206817,"S":1,"c":0,"h":19,"m":2},{"s":"opc-invoice-manager","r":"HIGH","f":15,"z":118871,"S":1,"c":0,"h":7,"m":10},{"s":"opc-contract-manager","r":"HIGH","f":14,"z":124044,"S":1,"c":0,"h":4,"m":7},{"s":"notion-api-skill","r":"HIGH","f":3,"z":13073,"S":0,"c":0,"h":25,"m":0},{"s":"pdf-editor-compdf","r":"HIGH","f":3,"z":16681,"S":0,"c":0,"h":17,"m":0},{"s":"tapd","r":"HIGH","f":4,"z":31758,"S":1,"c":0,"h":10,"m":0},{"s":"pdd-rebate","r":"HIGH","f":25,"z":223255,"S":1,"c":0,"h":75,"m":15},{"s":"tapd-api","r":"HIGH","f":9,"z":74900,"S":1,"c":0,"h":15,"m":4},{"s":"auto-updater-windows","r":"MEDIUM","f":4,"z":6270,"S":0,"c":0,"h":0,"m":3},{"s":"e2e-test-1773988426","r":"UNKNOWN","f":0,"z":0,"S":0,"c":0,"h":0,"m":0},{"s":"generate-daily-sports-update","r":"HIGH","f":2,"z":3061,"S":0,"c":0,"h":2,"m":1},{"s":"e2e-test-1773989186","r":"UNKNOWN","f":0,"z":0,"S":0,"c":0,"h":0,"m":0},{"s":"pfizer","r":"HIGH","f":2,"z":1636,"S":0,"c":0,"h":1,"m":0},{"s":"wells1137-skill-updater","r":"LOW","f":3,"z":2927,"S":1,"c":0,"h":0,"m":0},{"s":"ipfs-server","r":"HIGH","f":3,"z":9362,"S":0,"c":0,"h":6,"m":4},{"s":"tc-cheapflights","r":"HIGH","f":19,"z":122704,"S":1,"c":0,"h":26,"m":8},{"s":"stripfeed","r":"HIGH","f":2,"z":5317,"S":0,"c":0,"h":10,"m":0},{"s":"spf-write-plan","r":"HIGH","f":8,"z":10917,"S":0,"c":0,"h":2,"m":0},{"s":"spf-exec-plan","r":"LOW","f":2,"z":5497,"S":0,"c":0,"h":0,"m":0},{"s":"appflowy-skill","r":"HIGH","f":40,"z":132030,"S":1,"c":0,"h":12,"m":8},{"s":"campfire-prediction","r":"EXTREME","f":9,"z":39929,"S":0,"c":1,"h":38,"m":0},{"s":"spf-test-skill","r":"LOW","f":2,"z":1864,"S":0,"c":0,"h":0,"m":0},{"s":"dupfinder","r":"HIGH","f":3,"z":16066,"S":1,"c":0,"h":3,"m":3},{"s":"indigo-ipfs","r":"LOW","f":6,"z":13433,"S":0,"c":0,"h":0,"m":0},{"s":"weather-py","r":"HIGH","f":5,"z":50081,"S":1,"c":0,"h":9,"m":3},{"s":"pinata-api","r":"HIGH","f":2,"z":8261,"S":0,"c":0,"h":42,"m":0},{"s":"pinata-erc-8004","r":"HIGH","f":2,"z":29984,"S":0,"c":0,"h":25,"m":0},{"s":"comment-converter","r":"LOW","f":2,"z":1534,"S":0,"c":0,"h":0,"m":0},{"s":"gipformer","r":"HIGH","f":7,"z":35738,"S":1,"c":0,"h":7,"m":10},{"s":"deepfake-detection","r":"HIGH","f":2,"z":4548,"S":0,"c":0,"h":5,"m":0},{"s":"basecamp-cli-mcp","r":"HIGH","f":61,"z":610098,"S":1,"c":0,"h":625,"m":8},{"s":"tapform","r":"HIGH","f":2,"z":4522,"S":0,"c":0,"h":2,"m":1},{"s":"stepfun-step-audio-r1-1","r":"HIGH","f":6,"z":26416,"S":1,"c":0,"h":5,"m":7},{"s":"deepfocus","r":"HIGH","f":3,"z":15649,"S":1,"c":0,"h":1,"m":2},{"s":"otpforge","r":"HIGH","f":5,"z":17966,"S":1,"c":0,"h":1,"m":2},{"s":"millionfinney-homepage","r":"HIGH","f":5,"z":24329,"S":1,"c":0,"h":4,"m":0},{"s":"tmpfiles-upload","r":"HIGH","f":2,"z":2063,"S":0,"c":0,"h":3,"m":0},{"s":"tapfiliate","r":"HIGH","f":2,"z":4874,"S":0,"c":0,"h":2,"m":1},{"s":"faceswap","r":"HIGH","f":4,"z":11463,"S":0,"c":0,"h":16,"m":0},{"s":"tmpfiles-upload-stdlib","r":"HIGH","f":2,"z":5596,"S":0,"c":0,"h":3,"m":1},{"s":"storacha-upload","r":"HIGH","f":4,"z":23674,"S":1,"c":0,"h":22,"m":9},{"s":"klipfolio","r":"HIGH","f":2,"z":4597,"S":0,"c":0,"h":2,"m":1},{"s":"openclaw-fact-checker","r":"HIGH","f":8,"z":46991,"S":0,"c":0,"h":15,"m":2},{"s":"mind-security","r":"HIGH","f":4,"z":14964,"S":1,"c":0,"h":24,"m":0},{"s":"firstt","r":"HIGH","f":2,"z":45903,"S":0,"c":0,"h":18,"m":10},{"s":"outreach-scout","r":"LOW","f":5,"z":10543,"S":0,"c":0,"h":0,"m":0},{"s":"nexus-mcp-bridge","r":"HIGH","f":3,"z":4627,"S":0,"c":0,"h":12,"m":0},{"s":"pg","r":"LOW","f":2,"z":3830,"S":0,"c":0,"h":0,"m":0},{"s":"ai-content-detection","r":"HIGH","f":2,"z":16082,"S":0,"c":0,"h":15,"m":0},{"s":"pg-copilot","r":"HIGH","f":4,"z":60572,"S":1,"c":0,"h":6,"m":2},{"s":"discord-voice-memo-upgrade","r":"HIGH","f":11,"z":84603,"S":1,"c":0,"h":50,"m":15},{"s":"openclaw-setup","r":"EXTREME","f":3,"z":16294,"S":0,"c":2,"h":35,"m":11},{"s":"tcom-tripgenie-skill","r":"HIGH","f":2,"z":6097,"S":0,"c":0,"h":5,"m":0},{"s":"discord-voice-deepgram","r":"HIGH","f":13,"z":95233,"S":1,"c":0,"h":50,"m":9},{"s":"agent-rpg","r":"HIGH","f":7,"z":7236,"S":1,"c":0,"h":1,"m":2},{"s":"molt-rpg","r":"HIGH","f":10,"z":52345,"S":1,"c":0,"h":6,"m":1},{"s":"depguard","r":"HIGH","f":10,"z":47276,"S":1,"c":0,"h":255,"m":20},{"s":"multi-agent-tenant-upgrade","r":"HIGH","f":17,"z":130872,"S":1,"c":0,"h":62,"m":20},{"s":"next-upgrade","r":"HIGH","f":2,"z":2140,"S":0,"c":0,"h":4,"m":2},{"s":"pet-rpg","r":"HIGH","f":5,"z":27044,"S":1,"c":0,"h":1,"m":0},{"s":"snipgrapher","r":"LOW","f":4,"z":4739,"S":0,"c":0,"h":0,"m":0},{"s":"upgrade-openclaw","r":"LOW","f":4,"z":6494,"S":0,"c":0,"h":0,"m":0},{"s":"sovereign-rpg-xp-engine","r":"LOW","f":2,"z":2743,"S":0,"c":0,"h":0,"m":0},{"s":"paywall-upgrade-cro","r":"LOW","f":2,"z":8180,"S":0,"c":0,"h":0,"m":0},{"s":"openclaw-safe-upgrade","r":"HIGH","f":3,"z":26718,"S":1,"c":0,"h":17,"m":22},{"s":"deepgram-transcribe","r":"HIGH","f":3,"z":5647,"S":1,"c":0,"h":7,"m":0},{"s":"phone-agent","r":"HIGH","f":8,"z":51271,"S":1,"c":0,"h":23,"m":19},{"s":"tripgo-api","r":"HIGH","f":38,"z":101263,"S":1,"c":0,"h":156,"m":13},{"s":"paywall-upgrade-designer","r":"LOW","f":3,"z":17482,"S":0,"c":0,"h":0,"m":0},{"s":"skedgo-tripgo-api","r":"HIGH","f":38,"z":100639,"S":1,"c":0,"h":155,"m":13},{"s":"tripgenie","r":"HIGH","f":2,"z":6086,"S":0,"c":0,"h":5,"m":0},{"s":"claw-rpg","r":"HIGH","f":2,"z":2875,"S":0,"c":0,"h":4,"m":1},{"s":"openclaw-backupgg","r":"HIGH","f":4,"z":13343,"S":1,"c":0,"h":1,"m":11},{"s":"rpg-text","r":"LOW","f":20,"z":67904,"S":0,"c":0,"h":0,"m":0},{"s":"hap-upgrade","r":"HIGH","f":7,"z":46264,"S":0,"c":0,"h":30,"m":1},{"s":"voice-assistant","r":"HIGH","f":6,"z":43259,"S":1,"c":0,"h":12,"m":2},{"s":"k8s-capi","r":"LOW","f":2,"z":4716,"S":0,"c":0,"h":0,"m":0},{"s":"clawdbot-skill-clawdbot-workspace-template-review","r":"LOW","f":2,"z":2294,"S":0,"c":0,"h":0,"m":0},{"s":"deepgram-voice-workflow","r":"HIGH","f":8,"z":8939,"S":1,"c":0,"h":12,"m":1},{"s":"openclaw-context-upgrade","r":"LOW","f":2,"z":3190,"S":0,"c":0,"h":0,"m":0},{"s":"openclaw-vault","r":"HIGH","f":4,"z":70424,"S":1,"c":0,"h":11,"m":12},{"s":"upgrade-guardian","r":"HIGH","f":7,"z":49294,"S":0,"c":0,"h":1,"m":16},{"s":"openclaw-marshal","r":"EXTREME","f":4,"z":75069,"S":1,"c":2,"h":13,"m":7},{"s":"apex-agent","r":"HIGH","f":4,"z":16333,"S":0,"c":0,"h":1,"m":0},{"s":"openclaw-upgrader","r":"HIGH","f":5,"z":38718,"S":1,"c":0,"h":1,"m":13},{"s":"skill-upgrade-checker","r":"HIGH","f":3,"z":10114,"S":0,"c":0,"h":5,"m":0},{"s":"openclaw-workspace-governance-installer","r":"LOW","f":2,"z":3953,"S":0,"c":0,"h":0,"m":0},{"s":"openclaw-credential-manager","r":"HIGH","f":16,"z":118220,"S":1,"c":0,"h":29,"m":12},{"s":"klawarena","r":"HIGH","f":2,"z":26300,"S":0,"c":0,"h":45,"m":3},{"s":"openclaw-upgrade","r":"HIGH","f":2,"z":2207,"S":0,"c":0,"h":3,"m":0},{"s":"clawcall-ai","r":"HIGH","f":5,"z":103631,"S":1,"c":0,"h":150,"m":6},{"s":"dependency-upgrade-briefing","r":"EXTREME","f":10,"z":21144,"S":1,"c":1,"h":1,"m":3},{"s":"photos","r":"MEDIUM","f":2,"z":3505,"S":0,"c":0,"h":0,"m":1},{"s":"resume-screener-pro","r":"LOW","f":2,"z":9838,"S":0,"c":0,"h":0,"m":0},{"s":"photo-captions","r":"HIGH","f":3,"z":9825,"S":0,"c":0,"h":2,"m":0},{"s":"photo-restoration","r":"HIGH","f":3,"z":22579,"S":0,"c":0,"h":28,"m":0},{"s":"photo-scorer","r":"HIGH","f":8,"z":67355,"S":1,"c":0,"h":8,"m":20},{"s":"phog-cli","r":"HIGH","f":3,"z":11353,"S":0,"c":0,"h":3,"m":3},{"s":"clawpaw-phone-control","r":"HIGH","f":19,"z":53439,"S":1,"c":0,"h":8,"m":1},{"s":"daily-trending","r":"HIGH","f":2,"z":2715,"S":0,"c":0,"h":5,"m":0},{"s":"cnpj-lookup","r":"HIGH","f":7,"z":32833,"S":1,"c":0,"h":7,"m":2},{"s":"clawcall-phone","r":"HIGH","f":4,"z":11609,"S":0,"c":0,"h":17,"m":1},{"s":"npjames-apple-reminders","r":"MEDIUM","f":2,"z":2452,"S":0,"c":0,"h":0,"m":1},{"s":"npjames-apple-notes","r":"MEDIUM","f":2,"z":2021,"S":0,"c":0,"h":0,"m":1},{"s":"npjames-api-design","r":"LOW","f":3,"z":13494,"S":0,"c":0,"h":0,"m":0},{"s":"npjames-1password","r":"HIGH","f":4,"z":4258,"S":0,"c":0,"h":1,"m":0},{"s":"pkedge","r":"HIGH","f":2,"z":16593,"S":0,"c":0,"h":11,"m":2},{"s":"flipkart-seller-dashboard","r":"HIGH","f":2,"z":7614,"S":0,"c":0,"h":4,"m":1},{"s":"clawpk","r":"HIGH","f":5,"z":11788,"S":1,"c":0,"h":23,"m":0},{"s":"admet-prediction","r":"HIGH","f":5,"z":38548,"S":1,"c":0,"h":1,"m":5},{"s":"react-native-update","r":"MEDIUM","f":4,"z":7693,"S":1,"c":0,"h":0,"m":1},{"s":"pharma-pharmacology-agent","r":"HIGH","f":4,"z":16483,"S":1,"c":0,"h":2,"m":0},{"s":"apple-hig","r":"LOW","f":2,"z":13528,"S":0,"c":0,"h":0,"m":0},{"s":"hopkin-paid-ads","r":"HIGH","f":2,"z":5185,"S":0,"c":0,"h":1,"m":3},{"s":"autonomous-organization","r":"LOW","f":2,"z":1315,"S":0,"c":0,"h":0,"m":0},{"s":"pharmaclaw-pharmacology-agent","r":"HIGH","f":5,"z":29092,"S":1,"c":0,"h":4,"m":0},{"s":"maintenance","r":"HIGH","f":3,"z":15115,"S":1,"c":0,"h":3,"m":2},{"s":"india-price-tracker","r":"MEDIUM","f":12,"z":16258,"S":1,"c":0,"h":0,"m":2},{"s":"dingtalk-link-smb","r":"HIGH","f":2,"z":3134,"S":0,"c":0,"h":2,"m":1},{"s":"pm","r":"LOW","f":2,"z":1899,"S":0,"c":0,"h":0,"m":0},{"s":"wenjuan-survey","r":"EXTREME","f":53,"z":461560,"S":1,"c":1,"h":512,"m":33},{"s":"macos-hig-designer","r":"LOW","f":2,"z":23434,"S":0,"c":0,"h":0,"m":0},{"s":"teaching-plan-writer","r":"LOW","f":10,"z":42356,"S":0,"c":0,"h":0,"m":0},{"s":"pm-sim","r":"LOW","f":2,"z":490,"S":0,"c":0,"h":0,"m":0},{"s":"pm-skills-marketplace","r":"HIGH","f":2,"z":11850,"S":0,"c":0,"h":2,"m":4},{"s":"pmaster","r":"LOW","f":1,"z":29289,"S":0,"c":0,"h":0,"m":0},{"s":"pm-dashboard","r":"MEDIUM","f":2,"z":1585,"S":0,"c":0,"h":0,"m":1},{"s":"business-development","r":"HIGH","f":5,"z":28138,"S":1,"c":0,"h":16,"m":0},{"s":"subagent-driven-development","r":"LOW","f":5,"z":14946,"S":0,"c":0,"h":0,"m":0},{"s":"pmu-data-quality-skill","r":"MEDIUM","f":5,"z":27537,"S":1,"c":0,"h":0,"m":3},{"s":"clawpm","r":"LOW","f":2,"z":8016,"S":0,"c":0,"h":0,"m":0},{"s":"coding-pm","r":"HIGH","f":4,"z":25767,"S":0,"c":0,"h":4,"m":29},{"s":"capital-equipment","r":"HIGH","f":3,"z":5903,"S":0,"c":0,"h":2,"m":1},{"s":"piv","r":"HIGH","f":11,"z":40494,"S":0,"c":0,"h":1,"m":4},{"s":"agent-a-pm-skill","r":"HIGH","f":38,"z":149230,"S":1,"c":0,"h":6,"m":16},{"s":"ket","r":"LOW","f":2,"z":8897,"S":0,"c":0,"h":0,"m":0},{"s":"ai-pm-intel-brief","r":"LOW","f":4,"z":6656,"S":0,"c":0,"h":0,"m":0},{"s":"13-day-sprint-method","r":"HIGH","f":2,"z":24266,"S":0,"c":0,"h":2,"m":0},{"s":"continuity","r":"HIGH","f":4,"z":19904,"S":1,"c":0,"h":4,"m":1},{"s":"shopmind-price-compare","r":"HIGH","f":3,"z":15123,"S":1,"c":0,"h":3,"m":0},{"s":"api-development-expert","r":"LOW","f":2,"z":2072,"S":0,"c":0,"h":0,"m":0},{"s":"cpmo-daily-report","r":"HIGH","f":2,"z":10310,"S":0,"c":0,"h":2,"m":2},{"s":"inventory","r":"LOW","f":2,"z":3991,"S":0,"c":0,"h":0,"m":0},{"s":"vite","r":"HIGH","f":2,"z":4596,"S":0,"c":0,"h":1,"m":1},{"s":"capneteq-cesco345","r":"HIGH","f":3,"z":3430,"S":0,"c":0,"h":2,"m":1},{"s":"full-stack-feature","r":"MEDIUM","f":3,"z":12392,"S":0,"c":0,"h":0,"m":4},{"s":"agent-spm-setup-skill","r":"HIGH","f":2,"z":5088,"S":0,"c":0,"h":4,"m":1},{"s":"wechat-content-creator","r":"LOW","f":2,"z":6948,"S":0,"c":0,"h":0,"m":0},{"s":"esim","r":"LOW","f":2,"z":2895,"S":0,"c":0,"h":0,"m":0},{"s":"url2png","r":"HIGH","f":4,"z":1856,"S":1,"c":0,"h":5,"m":0},{"s":"png-lsb-skills","r":"HIGH","f":4,"z":16327,"S":1,"c":0,"h":1,"m":1},{"s":"wallet-pnl","r":"HIGH","f":19,"z":28302,"S":1,"c":0,"h":13,"m":6},{"s":"ppt2png","r":"MEDIUM","f":4,"z":5526,"S":1,"c":0,"h":0,"m":11},{"s":"m365-pnp-cli","r":"HIGH","f":2,"z":5172,"S":0,"c":0,"h":4,"m":2},{"s":"erpnext-frappe","r":"HIGH","f":17,"z":50702,"S":0,"c":0,"h":105,"m":0},{"s":"topnews","r":"HIGH","f":22,"z":93347,"S":1,"c":0,"h":11,"m":4},{"s":"ai-deepnews","r":"HIGH","f":3,"z":12197,"S":1,"c":0,"h":16,"m":2},{"s":"aipm-deepnews-daily","r":"HIGH","f":3,"z":12213,"S":1,"c":0,"h":16,"m":2},{"s":"pls-canvas-design","r":"LOW","f":2,"z":2198,"S":0,"c":0,"h":0,"m":0},{"s":"qr-code-generator","r":"HIGH","f":5,"z":52135,"S":1,"c":0,"h":45,"m":24},{"s":"stegstr","r":"HIGH","f":4,"z":6244,"S":1,"c":0,"h":10,"m":0},{"s":"mopng-api","r":"HIGH","f":5,"z":31630,"S":1,"c":0,"h":3,"m":12},{"s":"hyperliquid-dex","r":"HIGH","f":2,"z":4025,"S":0,"c":0,"h":3,"m":0},{"s":"adobeaitopng","r":"LOW","f":2,"z":5678,"S":0,"c":0,"h":0,"m":0},{"s":"screenshot-skill","r":"MEDIUM","f":4,"z":15230,"S":1,"c":0,"h":0,"m":8},{"s":"z-card-image","r":"HIGH","f":15,"z":40718,"S":1,"c":0,"h":5,"m":19},{"s":"grok-imagine-image-pro","r":"HIGH","f":2,"z":5527,"S":0,"c":0,"h":7,"m":3},{"s":"portfolio-report","r":"LOW","f":3,"z":4470,"S":0,"c":0,"h":0,"m":0},{"s":"svg-to-png","r":"HIGH","f":5,"z":20513,"S":1,"c":0,"h":11,"m":4},{"s":"a-share-daily-report","r":"HIGH","f":3,"z":49894,"S":1,"c":0,"h":4,"m":4},{"s":"prediction-bridge","r":"HIGH","f":3,"z":16332,"S":1,"c":0,"h":4,"m":2},{"s":"snapog","r":"HIGH","f":2,"z":5954,"S":0,"c":0,"h":10,"m":0},{"s":"excalidraw-creator","r":"HIGH","f":7,"z":67670,"S":1,"c":0,"h":82,"m":9},{"s":"tuebingen-weather-graphics","r":"HIGH","f":3,"z":5329,"S":1,"c":0,"h":1,"m":2},{"s":"gotchi-finder","r":"HIGH","f":20,"z":51796,"S":1,"c":0,"h":51,"m":23},{"s":"ppt-vision-replica","r":"HIGH","f":6,"z":46754,"S":1,"c":0,"h":4,"m":3},{"s":"erpnext","r":"HIGH","f":2,"z":6709,"S":0,"c":0,"h":2,"m":1},{"s":"excalidraw-canvas","r":"HIGH","f":2,"z":3332,"S":0,"c":0,"h":3,"m":1},{"s":"md2png","r":"MEDIUM","f":2,"z":4047,"S":0,"c":0,"h":0,"m":1},{"s":"skill-trading-journal","r":"LOW","f":2,"z":3969,"S":0,"c":0,"h":0,"m":0},{"s":"mermaid-image-generator","r":"HIGH","f":3,"z":7865,"S":1,"c":0,"h":8,"m":2},{"s":"opn","r":"HIGH","f":2,"z":4457,"S":0,"c":0,"h":2,"m":1},{"s":"mechanics-sketches","r":"MEDIUM","f":5,"z":15758,"S":1,"c":0,"h":0,"m":5},{"s":"canvas-design-pro","r":"HIGH","f":30,"z":142051,"S":0,"c":0,"h":5,"m":0},{"s":"portfolio-holdings-analyzer","r":"MEDIUM","f":4,"z":53386,"S":1,"c":0,"h":0,"m":1},{"s":"paper-trader","r":"HIGH","f":4,"z":37317,"S":1,"c":0,"h":39,"m":1},{"s":"ppt-icon-generator","r":"HIGH","f":6,"z":28064,"S":1,"c":0,"h":7,"m":2},{"s":"ppq-private-mode","r":"HIGH","f":2,"z":2454,"S":0,"c":0,"h":3,"m":0},{"s":"github-ops","r":"HIGH","f":2,"z":4256,"S":0,"c":0,"h":5,"m":0},{"s":"pump-fun-tokenized-agents","r":"HIGH","f":4,"z":23041,"S":0,"c":0,"h":12,"m":2},{"s":"market-sentiment-pulse","r":"LOW","f":3,"z":1849,"S":1,"c":0,"h":0,"m":0},{"s":"pve-automation","r":"EXTREME","f":4,"z":53228,"S":1,"c":1,"h":15,"m":5},{"s":"moltchan","r":"HIGH","f":2,"z":6987,"S":0,"c":0,"h":23,"m":0},{"s":"flow-n-intel","r":"HIGH","f":2,"z":9099,"S":0,"c":0,"h":3,"m":0},{"s":"whatsapp-voice-chat-integration-open-source","r":"HIGH","f":11,"z":42087,"S":1,"c":0,"h":16,"m":19},{"s":"enteriva-ai-social-hub","r":"HIGH","f":2,"z":25655,"S":0,"c":0,"h":63,"m":0},{"s":"product-hunt-launch","r":"HIGH","f":2,"z":931,"S":0,"c":0,"h":1,"m":0},{"s":"moltbook-2","r":"HIGH","f":2,"z":19781,"S":0,"c":0,"h":55,"m":0},{"s":"appveyor","r":"HIGH","f":2,"z":5885,"S":0,"c":0,"h":2,"m":1},{"s":"moltbook-voidborne","r":"HIGH","f":8,"z":5930,"S":1,"c":0,"h":12,"m":0},{"s":"agent-nou","r":"HIGH","f":3,"z":20121,"S":0,"c":0,"h":58,"m":0},{"s":"aulifox","r":"HIGH","f":5,"z":34498,"S":0,"c":0,"h":85,"m":1},{"s":"moltbook-backup","r":"HIGH","f":5,"z":34560,"S":0,"c":0,"h":86,"m":1},{"s":"lumos-auditor","r":"HIGH","f":4,"z":23372,"S":0,"c":0,"h":61,"m":0},{"s":"moltbook-skill","r":"HIGH","f":9,"z":8632,"S":1,"c":0,"h":8,"m":0},{"s":"npv","r":"HIGH","f":3,"z":7772,"S":1,"c":0,"h":1,"m":0},{"s":"apipick-ip-geolocation","r":"HIGH","f":4,"z":8997,"S":0,"c":0,"h":23,"m":0},{"s":"psyvector-pv25","r":"LOW","f":2,"z":827,"S":0,"c":0,"h":0,"m":0},{"s":"tpvl","r":"HIGH","f":10,"z":31863,"S":1,"c":0,"h":3,"m":1},{"s":"psyvector-pv27","r":"LOW","f":2,"z":816,"S":0,"c":0,"h":0,"m":0},{"s":"psyvector-pv13","r":"LOW","f":2,"z":843,"S":0,"c":0,"h":0,"m":0},{"s":"psyvector-pv32","r":"LOW","f":2,"z":812,"S":0,"c":0,"h":0,"m":0},{"s":"psyvector-pv33","r":"LOW","f":2,"z":825,"S":0,"c":0,"h":0,"m":0},{"s":"moltbook-trading-sniper","r":"HIGH","f":3,"z":4540,"S":1,"c":0,"h":11,"m":0},{"s":"psyvector-pv15","r":"LOW","f":2,"z":826,"S":0,"c":0,"h":0,"m":0},{"s":"wizwand-swarm","r":"HIGH","f":6,"z":61411,"S":0,"c":0,"h":101,"m":1},{"s":"china-renewable-energy-sourcing","r":"MEDIUM","f":4,"z":31698,"S":1,"c":0,"h":0,"m":1},{"s":"reddit-engagement","r":"HIGH","f":6,"z":30608,"S":0,"c":0,"h":2,"m":0},{"s":"burnerempire-arena","r":"HIGH","f":9,"z":115783,"S":1,"c":0,"h":141,"m":4},{"s":"moltbook04","r":"HIGH","f":2,"z":34423,"S":0,"c":0,"h":64,"m":0},{"s":"slopwork-marketplace","r":"HIGH","f":3,"z":31534,"S":0,"c":0,"h":17,"m":2},{"s":"upwork","r":"LOW","f":7,"z":8342,"S":0,"c":0,"h":0,"m":0},{"s":"upwork-hunting","r":"LOW","f":2,"z":7362,"S":0,"c":0,"h":0,"m":0},{"s":"upwork-automation-gig","r":"LOW","f":2,"z":903,"S":0,"c":0,"h":0,"m":0},{"s":"upwork-proposal-generator","r":"HIGH","f":2,"z":716,"S":0,"c":0,"h":1,"m":0},{"s":"upwork-automation-using-ai","r":"LOW","f":4,"z":5263,"S":0,"c":0,"h":0,"m":0},{"s":"deepwiki-mcp","r":"HIGH","f":7,"z":12525,"S":1,"c":0,"h":12,"m":1},{"s":"deepwiki-mcp-skill","r":"HIGH","f":5,"z":8285,"S":1,"c":0,"h":33,"m":1},{"s":"deepwiki-ask","r":"HIGH","f":5,"z":10076,"S":1,"c":0,"h":3,"m":7},{"s":"clawdgigs","r":"EXTREME","f":11,"z":74933,"S":1,"c":1,"h":26,"m":93},{"s":"sleepwell","r":"HIGH","f":5,"z":25170,"S":1,"c":0,"h":3,"m":3},{"s":"upwork-proposal-writer","r":"LOW","f":3,"z":3038,"S":0,"c":0,"h":0,"m":0},{"s":"sveltekit-webapp","r":"HIGH","f":8,"z":53573,"S":0,"c":0,"h":12,"m":7},{"s":"privateapp","r":"EXTREME","f":51,"z":355513,"S":1,"c":1,"h":110,"m":61},{"s":"helpwise","r":"HIGH","f":2,"z":5761,"S":0,"c":0,"h":2,"m":1},{"s":"freelance-proposal-engine","r":"LOW","f":2,"z":6257,"S":0,"c":0,"h":0,"m":0},{"s":"freelance-automation-gig","r":"LOW","f":2,"z":2076,"S":0,"c":0,"h":0,"m":0},{"s":"ai-upwork-proposal-writing-job-tracking-system","r":"HIGH","f":8,"z":44904,"S":1,"c":0,"h":70,"m":0},{"s":"appwrite","r":"HIGH","f":2,"z":5728,"S":0,"c":0,"h":2,"m":1},{"s":"create-plugin-deepwiki","r":"LOW","f":3,"z":6930,"S":0,"c":0,"h":0,"m":0},{"s":"stopwatch","r":"HIGH","f":3,"z":16393,"S":1,"c":0,"h":2,"m":3},{"s":"tiktok-page","r":"HIGH","f":2,"z":12691,"S":0,"c":0,"h":12,"m":1},{"s":"presale-one-pass-orchestrator","r":"LOW","f":3,"z":1546,"S":0,"c":0,"h":0,"m":0},{"s":"hotbutter","r":"HIGH","f":7,"z":15657,"S":1,"c":0,"h":20,"m":3},{"s":"instagram-page","r":"HIGH","f":2,"z":12916,"S":0,"c":0,"h":13,"m":0},{"s":"canary-sr","r":"EXTREME","f":10,"z":85395,"S":1,"c":10,"h":12,"m":10},{"s":"x-page","r":"HIGH","f":2,"z":13961,"S":0,"c":0,"h":9,"m":0},{"s":"freelance-proposal-writer","r":"LOW","f":2,"z":3644,"S":0,"c":0,"h":0,"m":0},{"s":"proposal-copilot","r":"HIGH","f":3,"z":12319,"S":1,"c":0,"h":14,"m":0},{"s":"rdk-x5-gpio","r":"HIGH","f":2,"z":3665,"S":0,"c":0,"h":15,"m":0},{"s":"openclaw-shield-upx","r":"HIGH","f":3,"z":14546,"S":0,"c":0,"h":17,"m":1},{"s":"lpxpoly","r":"HIGH","f":2,"z":3843,"S":0,"c":0,"h":15,"m":0},{"s":"acpx-orchestrator","r":"LOW","f":6,"z":8701,"S":0,"c":0,"h":0,"m":0},{"s":"acpx-codex-playbook","r":"HIGH","f":4,"z":7915,"S":0,"c":0,"h":3,"m":2},{"s":"bifrost-slpx-stake","r":"HIGH","f":2,"z":11835,"S":0,"c":0,"h":14,"m":0}]