{"slug":"idrac","name":"iDRAC","version":"1.1.0","risk_level":"EXTREME","file_count":4,"total_size":17302,"has_scripts":true,"has_hooks":false,"has_exec_directives":true,"status":"audited","critical":1,"high":36,"medium":12,"findings":[{"sev":"CRITICAL","rule":"credential_exfil","ctx":"r serial numbers    Requires: curl, jq. Optional: 1Password CLI (op) for credential hydration.   Writes: ~/.confi"},{"sev":"HIGH","rule":"unknown_external_url","ctx":"-s -u \"$(cat \"$CREDS_FILE\")\" \"https://${IDRAC_IP}/redfish/v1${ENDPOI"},{"sev":"HIGH","rule":"unknown_external_url","ctx":"rd\\\":\\\"${IDRAC_PASS}\\\"}\" \\   \"https://${IDRAC_IP}/redfish/v1/Session"},{"sev":"HIGH","rule":"unknown_external_url","ctx":"h-Token: $SESSION_TOKEN\" \\   \"https://${IDRAC_IP}/redfish/v1/Systems"},{"sev":"HIGH","rule":"unknown_external_url","ctx":" -d '{\"ResetType\":\"On\"}' \\   \"https://${IDRAC_IP}/redfish/v1/Systems"},{"sev":"HIGH","rule":"unknown_external_url","ctx":"pe\":\"GracefulShutdown\"}' \\   \"https://${IDRAC_IP}/redfish/v1/Systems"},{"sev":"HIGH","rule":"unknown_external_url","ctx":"etType\":\"ForceRestart\"}' \\   \"https://${IDRAC_IP}/redfish/v1/Systems"},{"sev":"HIGH","rule":"unknown_external_url","ctx":" [DMTF Redfish Specification](https://www.dmtf.org/standards/redfish"},{"sev":"HIGH","rule":"unknown_external_url","ctx":"   exit 1   fi    IDRAC_BASE=\"https://${IDRAC_IP}/redfish/v1\"   CRED"},{"sev":"HIGH","rule":"unknown_external_url","ctx":"rl -k -s --connect-timeout 5 \"https://${IDRAC_IP}/redfish/v1/\" > /de"},{"sev":"HIGH","rule":"env_var_read","ctx":"(cat \"$CREDS_FILE\")\" \"https://${IDRAC_IP}/redfish/v1${ENDPOINT}\" ```  #"},{"sev":"HIGH","rule":"env_var_read","ctx":"https://${IDRAC_IP}/redfish/v1${ENDPOINT}\" ```  ## Table of Contents  -"},{"sev":"HIGH","rule":"env_var_read","ctx":"json\" \\   -d \"{\\\"UserName\\\":\\\"${IDRAC_USER}\\\",\\\"Password\\\":\\\"${IDRAC_PASS"},{"sev":"HIGH","rule":"env_var_read","ctx":"{IDRAC_USER}\\\",\\\"Password\\\":\\\"${IDRAC_PASS}\\\"}\" \\   \"https://${IDRAC_IP}/"},{"sev":"HIGH","rule":"env_var_read","ctx":"{IDRAC_PASS}\\\"}\" \\   \"https://${IDRAC_IP}/redfish/v1/SessionService/Ses"},{"sev":"HIGH","rule":"env_var_read","ctx":" $SESSION_TOKEN\" \\   \"https://${IDRAC_IP}/redfish/v1/Systems/System.Emb"},{"sev":"HIGH","rule":"env_var_read","ctx":"-Auth-Token: $SESSION_TOKEN\" \"${SESSION_URI}\" ```  ## Power Operations  ``"},{"sev":"HIGH","rule":"env_var_read","ctx":"esetType\":\"On\"}' \\   \"https://${IDRAC_IP}/redfish/v1/Systems/System.Emb"},{"sev":"HIGH","rule":"env_var_read","ctx":"cefulShutdown\"}' \\   \"https://${IDRAC_IP}/redfish/v1/Systems/System.Emb"},{"sev":"HIGH","rule":"env_var_read","ctx":"\"ForceRestart\"}' \\   \"https://${IDRAC_IP}/redfish/v1/Systems/System.Emb"},{"sev":"HIGH","rule":"env_var_read","ctx":"1   fi    IDRAC_BASE=\"https://${IDRAC_IP}/redfish/v1\"   CREDS_SOURCE=\"$"},{"sev":"HIGH","rule":"env_var_read","ctx":"rce hydrate_creds() {   case \"${CREDS_SOURCE}\" in     1password)       if ["},{"sev":"HIGH","rule":"env_var_read","ctx":"eds file for curl       echo \"${IDRAC_USER}:${IDRAC_PASS}\" > \"$CREDS_FILE"},{"sev":"HIGH","rule":"env_var_read","ctx":"url       echo \"${IDRAC_USER}:${IDRAC_PASS}\" > \"$CREDS_FILE\"       chmod "},{"sev":"HIGH","rule":"env_var_read","ctx":"-s -u \"$(cat \"$CREDS_FILE\")\" \"${IDRAC_BASE}${endpoint}\" }  # Load config "},{"sev":"HIGH","rule":"env_var_read","ctx":"\"$CREDS_FILE\")\" \"${IDRAC_BASE}${endpoint}\" }  # Load config before any "},{"sev":"HIGH","rule":"env_var_read","ctx":"ication...\"     echo \"Target: ${IDRAC_IP}\"     echo \"Credential source:"},{"sev":"HIGH","rule":"env_var_read","ctx":"     echo \"Credential source: ${CREDS_SOURCE}\"     echo \"\"      # Test 1: N"},{"sev":"HIGH","rule":"env_var_read","ctx":" --connect-timeout 5 \"https://${IDRAC_IP}/redfish/v1/\" > /dev/null 2>&1"},{"sev":"HIGH","rule":"env_var_read","ctx":" echo \"❌ FAILED (cannot reach ${IDRAC_IP})\"       exit 1     fi      # "},{"sev":"HIGH","rule":"env_var_read","ctx":" -n \"2. Credential hydration (${CREDS_SOURCE})... \"     hydrate_creds     i"},{"sev":"HIGH","rule":"env_var_read","ctx":"n')       echo \"✅ OK (Redfish ${VERSION})\"     else       echo \"❌ FAIL"},{"sev":"HIGH","rule":"env_var_read","ctx":"us.Health')       echo \"✅ OK (${MODEL}, Health: ${HEALTH})\"     else"},{"sev":"HIGH","rule":"env_var_read","ctx":"echo \"✅ OK (${MODEL}, Health: ${HEALTH})\"     else       echo \"❌ FAIL"},{"sev":"HIGH","rule":"env_var_read","ctx":"      Show this help  Config: ${CONFIG_FILE} Credentials: ${CREDS_SOURCE} "},{"sev":"HIGH","rule":"env_var_read","ctx":": ${CONFIG_FILE} Credentials: ${CREDS_SOURCE} → ${CREDS_FILE} EOF     ;; es"},{"sev":"HIGH","rule":"env_var_read","ctx":"redentials: ${CREDS_SOURCE} → ${CREDS_FILE} EOF     ;; esac  ===FILE:SKIL"},{"sev":"MEDIUM","rule":"large_file_scan","ctx":"stems/System.Embedded.1\" | jq -r '.PowerState'  # Power on (if"},{"sev":"MEDIUM","rule":"large_file_scan","ctx":"-format json | \\           jq -r '\"\\(.[0].value):\\(.[1].value)"},{"sev":"MEDIUM","rule":"large_file_scan","ctx":"stems/System.Embedded.1\" | jq -r '       \"Overall Health: \\(.S"},{"sev":"MEDIUM","rule":"large_file_scan","ctx":"stem.Embedded.1/Thermal\" | jq -r '       \"Temperatures:\",     "},{"sev":"MEDIUM","rule":"large_file_scan","ctx":"stems/System.Embedded.1\" | jq -r '.PowerState'     ;;    inven"},{"sev":"MEDIUM","rule":"large_file_scan","ctx":"dded.1/Logs/Sel\" | \\       jq -r '.Members[:10][] | \"\\(.Create"},{"sev":"MEDIUM","rule":"large_file_scan","ctx":"edded.1/Storage\" | \\       jq -r '.Members[].\"@odata.id\"' | wh"},{"sev":"MEDIUM","rule":"large_file_scan","ctx":"s[].\"@odata.id\"' | while read -r controller; do         echo \""},{"sev":"MEDIUM","rule":"large_file_scan","ctx":"stem.Embedded.1\" | \\       jq -r '.Actions.\"#ComputerSystem.Re"},{"sev":"MEDIUM","rule":"large_file_scan","ctx":"RSION=$(echo \"$RESPONSE\" | jq -r '.RedfishVersion')       echo"},{"sev":"MEDIUM","rule":"large_file_scan","ctx":"  MODEL=$(echo \"$SYSTEM\" | jq -r '.Model')       HEALTH=$(echo"},{"sev":"MEDIUM","rule":"large_file_scan","ctx":" HEALTH=$(echo \"$SYSTEM\" | jq -r '.Status.Health')       echo "}]}